cybrid_api_bank/__init__.py
cybrid_api_bank/api_client.py
cybrid_api_bank/configuration.py
cybrid_api_bank/exceptions.py
cybrid_api_bank/model_utils.py
cybrid_api_bank/rest.py
cybrid_api_bank/api/__init__.py
cybrid_api_bank/api/accounts_bank_api.py
cybrid_api_bank/api/assets_bank_api.py
cybrid_api_bank/api/banks_bank_api.py
cybrid_api_bank/api/counterparties_bank_api.py
cybrid_api_bank/api/customers_bank_api.py
cybrid_api_bank/api/deposit_addresses_bank_api.py
cybrid_api_bank/api/deposit_bank_accounts_bank_api.py
cybrid_api_bank/api/executions_bank_api.py
cybrid_api_bank/api/external_bank_accounts_bank_api.py
cybrid_api_bank/api/external_wallets_bank_api.py
cybrid_api_bank/api/files_bank_api.py
cybrid_api_bank/api/identity_verifications_bank_api.py
cybrid_api_bank/api/invoices_bank_api.py
cybrid_api_bank/api/payment_instructions_bank_api.py
cybrid_api_bank/api/persona_sessions_bank_api.py
cybrid_api_bank/api/plans_bank_api.py
cybrid_api_bank/api/prices_bank_api.py
cybrid_api_bank/api/quotes_bank_api.py
cybrid_api_bank/api/symbols_bank_api.py
cybrid_api_bank/api/trades_bank_api.py
cybrid_api_bank/api/transfers_bank_api.py
cybrid_api_bank/api/workflows_bank_api.py
cybrid_api_bank/apis/__init__.py
cybrid_api_bank/model/__init__.py
cybrid_api_bank/model/account.py
cybrid_api_bank/model/account_association.py
cybrid_api_bank/model/account_list.py
cybrid_api_bank/model/account_state.py
cybrid_api_bank/model/account_type.py
cybrid_api_bank/model/activity_limit.py
cybrid_api_bank/model/activity_side.py
cybrid_api_bank/model/activity_type.py
cybrid_api_bank/model/asset.py
cybrid_api_bank/model/asset_list.py
cybrid_api_bank/model/asset_types.py
cybrid_api_bank/model/bank.py
cybrid_api_bank/model/bank_feature.py
cybrid_api_bank/model/bank_list.py
cybrid_api_bank/model/bank_supported_payout_symbols_inner.py
cybrid_api_bank/model/bank_type.py
cybrid_api_bank/model/compliance_check.py
cybrid_api_bank/model/compliance_check_outcome.py
cybrid_api_bank_python-0.126.83.dist-info/METADATA
cybrid_api_bank_python-0.126.83.dist-info/WHEEL
cybrid_api_bank_python-0.126.83.dist-info/top_level.txt
cybrid_api_bank_python-0.126.83.dist-info/RECORD
